{
  "producto_660_58_15_412026": {
    "categoria": "frenos",
    "id": "producto_660_58_15_412026",
    "producto": "Hidrolavadora Electrica Trent HLT307 1400W Alta presion 1600 Psi 110 Bar con Accesorios",
    "precio": "10200",
    "descripcion": "hola soy un producto de prueba",
    "img": [
      "imagen_0_660_58_15_412026.jpg",
      "imagen_1_660_58_15_412026.jpg",
      "imagen_2_660_58_15_412026.jpg",
      "imagen_3_660_58_15_412026.jpg",
      "imagen_4_660_58_15_412026.jpg"
    ]
  }
}